parsearg/__init__.py
parsearg/data_structures.py
parsearg/example_trees.py
parsearg/parser.py
parsearg/utils.py
parsearg/version.py
parsearg-0.3.9.dist-info/LICENSE
parsearg-0.3.9.dist-info/METADATA
parsearg-0.3.9.dist-info/WHEEL
parsearg-0.3.9.dist-info/top_level.txt
parsearg-0.3.9.dist-info/RECORD
