Metadata-Version: 2.1
Name: parsearg
Version: 0.3.9
Summary: parsearg turns argparse on its head the declarative way
Home-page: https://github.com/tharte/parsearg
Author: Thomas P. Harte
Author-email: tharte@cantab.net
Maintainer: Thomas P. Harte
Maintainer-email: tharte@cantab.net
License: MIT
Keywords: CLI,subcommand,parser,argparse
Classifier: Programming Language :: Python :: 3
Classifier: License :: OSI Approved :: MIT License
Classifier: Operating System :: OS Independent
Requires-Python: >=3.6
License-File: LICENSE
